pyconsoler/__init__.py
pyconsoler/cli.py
pyconsoler/const.py
pyconsoler/helpers.py
pyconsoler/output.py
pyconsoler-0.2.10.dist-info/entry_points.txt
pyconsoler-0.2.10.dist-info/LICENSE
pyconsoler-0.2.10.dist-info/WHEEL
pyconsoler-0.2.10.dist-info/METADATA
pyconsoler-0.2.10.dist-info/RECORD
