Metadata-Version: 2.1
Name: pyconsoler
Version: 0.2.10
Summary: Helper classes and methods for console output
Home-page: https://github.com/sander76/consoler
License: UNKNOWN
Author: Sander Teunissen
Author-email: no_mail@nomail.com
Requires-Python: >=3.6
Classifier: License :: OSI Approved :: MIT License
Requires-Dist: colorama
